LICENSE.txt
README.md
setup.cfg
setup.py
EpisodeFixer/Episode.py
EpisodeFixer/EpisodeFixer.py
EpisodeFixer/Parsers.py
EpisodeFixer/Rename.py
EpisodeFixer/Subtitle.py
EpisodeFixer/TVShow.py
EpisodeFixer/UserInput.py
EpisodeFixer/__init__.py
EpisodeFixer.egg-info/PKG-INFO
EpisodeFixer.egg-info/SOURCES.txt
EpisodeFixer.egg-info/dependency_links.txt
EpisodeFixer.egg-info/entry_points.txt
EpisodeFixer.egg-info/requires.txt
EpisodeFixer.egg-info/top_level.txt