Metadata-Version: 2.1
Name: EpisodeFixer
Version: 1.0.2
Summary: An Episode Fixer which can embed subtitles and rename episodes.
Home-page: https://github.com/jainvasu631/EpisodeFixer
Author: Vasu Jain
Author-email: jain.vasu.631@gmail.com
License: UNKNOWN
Download-URL: https://github.com/jainvasu631/EpisodeFixer/archive/v1.0.2.tar.gz
Platform: UNKNOWN
Classifier: Programming Language :: Python :: 3
Classifier: License :: OSI Approved :: MIT License
Classifier: Operating System :: OS Independent
Classifier: Natural Language :: English
